bitmap/__init__.py
bitmap/core.py
greko-0.1.0.dist-info/licenses/LICENSE
greko-0.1.0.dist-info/METADATA
greko-0.1.0.dist-info/WHEEL
greko-0.1.0.dist-info/top_level.txt
greko-0.1.0.dist-info/RECORD
