Metadata-Version: 2.4
Name: greko
Version: 0.1.0
Summary: A package to process raw camera data into 1-bit bitmap images
Home-page: https://github.com/yourusername/bitmap
Author: Your Name
Author-email: your.email@example.com
Classifier: Programming Language :: Python :: 3
Classifier: License :: OSI Approved :: MIT License
Classifier: Operating System :: OS Independent
Requires-Python: >=3.6
License-File: LICENSE
Requires-Dist: rawpy>=0.17.0
Requires-Dist: pillow>=9.0.0
Requires-Dist: numpy>=1.21.0
Dynamic: author
Dynamic: author-email
Dynamic: classifier
Dynamic: description
Dynamic: description-content-type
Dynamic: home-page
Dynamic: license-file
Dynamic: requires-dist
Dynamic: requires-python
Dynamic: summary
